tkVFD/CharLUTs.py
tkVFD/Utils.py
tkVFD/__init__.py
tkVFD/seg16.py
tkVFD/seg7.py
tkVFD/Graphics/seg16/Grid.png
tkVFD/Graphics/seg16/segA1_off.png
tkVFD/Graphics/seg16/segA1_on.png
tkVFD/Graphics/seg16/segA2_off.png
tkVFD/Graphics/seg16/segA2_on.png
tkVFD/Graphics/seg16/segB_off.png
tkVFD/Graphics/seg16/segB_on.png
tkVFD/Graphics/seg16/segCC_off.png
tkVFD/Graphics/seg16/segCC_on.png
tkVFD/Graphics/seg16/segC_off.png
tkVFD/Graphics/seg16/segC_on.png
tkVFD/Graphics/seg16/segD1_off.png
tkVFD/Graphics/seg16/segD1_on.png
tkVFD/Graphics/seg16/segD2_off.png
tkVFD/Graphics/seg16/segD2_on.png
tkVFD/Graphics/seg16/segDP_off.png
tkVFD/Graphics/seg16/segDP_on.png
tkVFD/Graphics/seg16/segE_off.png
tkVFD/Graphics/seg16/segE_on.png
tkVFD/Graphics/seg16/segF_off.png
tkVFD/Graphics/seg16/segF_on.png
tkVFD/Graphics/seg16/segG1_off.png
tkVFD/Graphics/seg16/segG1_on.png
tkVFD/Graphics/seg16/segG2_off.png
tkVFD/Graphics/seg16/segG2_on.png
tkVFD/Graphics/seg16/segH_off.png
tkVFD/Graphics/seg16/segH_on.png
tkVFD/Graphics/seg16/segI_off.png
tkVFD/Graphics/seg16/segI_on.png
tkVFD/Graphics/seg16/segJ_off.png
tkVFD/Graphics/seg16/segJ_on.png
tkVFD/Graphics/seg16/segK_off.png
tkVFD/Graphics/seg16/segK_on.png
tkVFD/Graphics/seg16/segL_off.png
tkVFD/Graphics/seg16/segL_on.png
tkVFD/Graphics/seg16/segM_off.png
tkVFD/Graphics/seg16/segM_on.png
tkVFD/Graphics/seg7/Grid.png
tkVFD/Graphics/seg7/segA_off.png
tkVFD/Graphics/seg7/segA_on.png
tkVFD/Graphics/seg7/segB_off.png
tkVFD/Graphics/seg7/segB_on.png
tkVFD/Graphics/seg7/segCC_off.png
tkVFD/Graphics/seg7/segCC_on.png
tkVFD/Graphics/seg7/segC_off.png
tkVFD/Graphics/seg7/segC_on.png
tkVFD/Graphics/seg7/segDP_off.png
tkVFD/Graphics/seg7/segDP_on.png
tkVFD/Graphics/seg7/segD_off.png
tkVFD/Graphics/seg7/segD_on.png
tkVFD/Graphics/seg7/segE_off.png
tkVFD/Graphics/seg7/segE_on.png
tkVFD/Graphics/seg7/segF_off.png
tkVFD/Graphics/seg7/segF_on.png
tkVFD/Graphics/seg7/segG_off.png
tkVFD/Graphics/seg7/segG_on.png
tkVFD-1.1.0.dist-info/LICENSE.md
tkVFD-1.1.0.dist-info/METADATA
tkVFD-1.1.0.dist-info/WHEEL
tkVFD-1.1.0.dist-info/top_level.txt
tkVFD-1.1.0.dist-info/RECORD
