Metadata-Version: 2.1
Name: tkVFD
Version: 1.1.0
Summary: The tkVFD module allows for easy inclusion of customizable segmented alpha-numeric displays into any Tkinter application and supports both 16-segment and 7-segment geometries.
Author-email: "Andrew G." <andrewdget@gmail.com>
Maintainer-email: "Andrew G." <andrewdget@gmail.com>
License: MIT License
Project-URL: Homepage, https://github.com/andrewdget/tkVFD
Project-URL: Issues, https://github.com/andrewdget/tkVFD/issues
Keywords: tkinter,tk,VFD,Vacuum Fluorescent Display,LCD,Liquid Crystal Display,python,display
Classifier: Programming Language :: Python :: 3
Classifier: License :: OSI Approved :: MIT License
Classifier: Operating System :: OS Independent
Requires-Python: >=3.11
License-File: LICENSE.md
Requires-Dist: pillow
